TermQR/QR.py
TermQR/__init__.py
TermQR/term.py
TermQR-1.0.1.dist-info/METADATA
TermQR-1.0.1.dist-info/WHEEL
TermQR-1.0.1.dist-info/top_level.txt
TermQR-1.0.1.dist-info/RECORD
