Metadata-Version: 2.1
Name: TermQR
Version: 1.0.1
Summary: Draw a QRCode in termux.
Home-page: https://github.com/MoYeRanqianzhi/TermQR
Author: MoYeRanQianZhi
Author-email: MoYeRanQianZhi@gmail.com
License: MIT
Requires-Dist: qrcode (>=7.4.2)
Requires-Dist: colorama (>=0.4.6)
Requires-Dist: Pillow (>=9.4.0)
